networkcommander/__init__.py
networkcommander/config.py
networkcommander/deploy.py
networkcommander/device.py
networkcommander/device_executer.py
networkcommander/init.py
networkcommander/io_utils.py
networkcommander/keepass.py
networkcommander/main.py
networkcommander-0.4.7.dist-info/entry_points.txt
networkcommander-0.4.7.dist-info/LICENSE
networkcommander-0.4.7.dist-info/METADATA
networkcommander-0.4.7.dist-info/WHEEL
networkcommander-0.4.7.dist-info/RECORD
