Metadata-Version: 2.1
Name: NetworkCommander
Version: 0.4.7
Summary: cli scraping tools for network devices 
Author: Ido Don
Author-email: 76511079+Ido-Don@users.noreply.github.com
Requires-Python: >=3.9.0,<3.12
Classifier: Programming Language :: Python :: 3
Classifier: Programming Language :: Python :: 3.9
Classifier: Programming Language :: Python :: 3.10
Classifier: Programming Language :: Python :: 3.11
Requires-Dist: netmiko (>=4.3.0,<5.0.0)
Requires-Dist: pykeepass (>=4.0.6,<5.0.0)
Requires-Dist: typer[all] (>=0.9.0,<0.10.0)
